philipstv_gui/__init__.py
philipstv_gui/__main__.py
philipstv_gui/_version.py
philipstv_gui/ambilight.py
philipstv_gui/app.py
philipstv_gui/applications.py
philipstv_gui/channels.py
philipstv_gui/connector.py
philipstv_gui/errors.py
philipstv_gui/frame.py
philipstv_gui/remote.py
philipstv_gui/storage.py
philipstv_gui-2.0.1.dist-info/METADATA
philipstv_gui-2.0.1.dist-info/WHEEL
philipstv_gui-2.0.1.dist-info/entry_points.txt
philipstv_gui-2.0.1.dist-info/licenses/LICENSE
philipstv_gui-2.0.1.dist-info/RECORD
