Metadata-Version: 2.4
Name: philipstv-gui
Version: 2.0.1
Summary: GUI remote for Philips Android-powered TVs.
Project-URL: repository, https://github.com/bcyran/philipstv-gui
Maintainer-email: Bazyli Cyran <bazyli@cyran.dev>
License: MIT
License-File: LICENSE
Keywords: ambilight,gui,philips,remote,tv
Classifier: Intended Audience :: End Users/Desktop
Classifier: License :: OSI Approved :: MIT License
Classifier: Programming Language :: Python :: 3 :: Only
Classifier: Programming Language :: Python :: 3.10
Classifier: Programming Language :: Python :: 3.11
Classifier: Programming Language :: Python :: 3.12
Classifier: Programming Language :: Python :: 3.13
Classifier: Programming Language :: Python :: 3.14
Requires-Python: >=3.10
Requires-Dist: appdirs>=1.4.4
Requires-Dist: philipstv>=0.4
Requires-Dist: ttkbootstrap>=1.7.3
